{"cameraMode":{"drawMode":0,"name":"Shaded","section":"Shading Mode"},"sceneLighting":false,"audioPlay":false,"sceneViewState":{"m_AlwaysRefresh":false,"showFog":true,"showSkybox":false,"showFlares":true,"showImageEffects":true,"showParticleSystems":true,"showVisualEffectGraphs":true,"m_FxEnabled":true},"in2DMode":false,"pivot":{"x":-27.28474998474121,"y":2.1411643028259279,"z":-40.68318176269531},"rotation":{"x":-0.5222005844116211,"y":-0.37451881170272829,"z":0.2733488082885742,"w":-0.7158217430114746},"size":1.610555648803711,"orthographic":false}